{
  "annotations": {
    "list": [
      {
        "builtIn": 1,
        "datasource": {
          "type": "grafana",
          "uid": "-- Grafana --"
        },
        "enable": true,
        "hide": true,
        "iconColor": "rgba(0, 211, 255, 1)",
        "name": "Annotations & Alerts",
        "target": {
          "limit": 100,
          "matchAny": false,
          "tags": [],
          "type": "dashboard"
        },
        "type": "dashboard"
      }
    ]
  },
  "editable": true,
  "fiscalYearStartMonth": 0,
  "graphTooltip": 0,
  "id": 1,
  "links": [],
  "liveNow": false,
  "panels": [
    {
      "datasource": {
        "type": "influxdb",
        "uid": "influxdb"
      },
      "fieldConfig": {
        "defaults": {
          "color": {
            "mode": "palette-classic"
          },
          "custom": {
            "axisCenteredZero": false,
            "axisColorMode": "text",
            "axisLabel": "",
            "axisPlacement": "auto",
            "barAlignment": 0,
            "drawStyle": "line",
            "fillOpacity": 10,
            "gradientMode": "none",
            "hideFrom": {
              "legend": false,
              "tooltip": false,
              "viz": false
            },
            "lineInterpolation": "linear",
            "lineWidth": 1,
            "pointSize": 5,
            "scaleDistribution": {
              "type": "linear"
            },
            "showPoints": "auto",
            "spanNulls": false,
            "stacking": {
              "group": "A",
              "mode": "none"
            },
            "thresholdsStyle": {
              "mode": "off"
            }
          },
          "mappings": [],
          "thresholds": {
            "mode": "absolute",
            "steps": [
              {
                "color": "green",
                "value": null
              },
              {
                "color": "red",
                "value": 30
              }
            ]
          },
          "unit": "celsius"
        },
        "overrides": []
      },
      "gridPos": {
        "h": 8,
        "w": 12,
        "x": 0,
        "y": 0
      },
      "id": 2,
      "options": {
        "legend": {
          "calcs": [],
          "displayMode": "list",
          "placement": "bottom",
          "showLegend": true
        },
        "tooltip": {
          "mode": "single",
          "sort": "none"
        }
      },
      "targets": [
        {
          "datasource": {
            "type": "influxdb",
            "uid": "influxdb"
          },
          "query": "from(bucket: \"device_data\")\n  |> range(start: v.timeRangeStart, stop: v.timeRangeStop)\n  |> filter(fn: (r) => r[\"_measurement\"] == \"sensors\")\n  |> filter(fn: (r) => r[\"_field\"] == \"temperature\")\n  |> aggregateWindow(every: v.windowPeriod, fn: mean, createEmpty: false)",
          "refId": "A"
        }
      ],
      "title": "温度趋势",
      "type": "timeseries"
    },
    {
      "datasource": {
        "type": "influxdb",
        "uid": "influxdb"
      },
      "fieldConfig": {
        "defaults": {
          "color": {
            "mode": "palette-classic"
          },
          "custom": {
            "axisCenteredZero": false,
            "axisColorMode": "text",
            "axisLabel": "",
            "axisPlacement": "auto",
            "barAlignment": 0,
            "drawStyle": "line",
            "fillOpacity": 10,
            "gradientMode": "none",
            "hideFrom": {
              "legend": false,
              "tooltip": false,
              "viz": false
            },
            "lineInterpolation": "linear",
            "lineWidth": 1,
            "pointSize": 5,
            "scaleDistribution": {
              "type": "linear"
            },
            "showPoints": "auto",
            "spanNulls": false,
            "stacking": {
              "group": "A",
              "mode": "none"
            },
            "thresholdsStyle": {
              "mode": "off"
            }
          },
          "mappings": [],
          "thresholds": {
            "mode": "absolute",
            "steps": [
              {
                "color": "green",
                "value": null
              },
              {
                "color": "red",
                "value": 80
              }
            ]
          },
          "unit": "percent"
        },
        "overrides": []
      },
      "gridPos": {
        "h": 8,
        "w": 12,
        "x": 12,
        "y": 0
      },
      "id": 3,
      "options": {
        "legend": {
          "calcs": [],
          "displayMode": "list",
          "placement": "bottom",
          "showLegend": true
        },
        "tooltip": {
          "mode": "single",
          "sort": "none"
        }
      },
      "targets": [
        {
          "datasource": {
            "type": "influxdb",
            "uid": "influxdb"
          },
          "query": "from(bucket: \"device_data\")\n  |> range(start: v.timeRangeStart, stop: v.timeRangeStop)\n  |> filter(fn: (r) => r[\"_measurement\"] == \"sensors\")\n  |> filter(fn: (r) => r[\"_field\"] == \"humidity\")\n  |> aggregateWindow(every: v.windowPeriod, fn: mean, createEmpty: false)",
          "refId": "A"
        }
      ],
      "title": "湿度趋势",
      "type": "timeseries"
    },
    {
      "datasource": {
        "type": "influxdb",
        "uid": "influxdb"
      },
      "fieldConfig": {
        "defaults": {
          "color": {
            "mode": "thresholds"
          },
          "mappings": [],
          "max": 35,
          "min": 0,
          "thresholds": {
            "mode": "absolute",
            "steps": [
              {
                "color": "blue",
                "value": null
              },
              {
                "color": "green",
                "value": 15
              },
              {
                "color": "yellow",
                "value": 25
              },
              {
                "color": "red",
                "value": 30
              }
            ]
          },
          "unit": "celsius"
        },
        "overrides": []
      },
      "gridPos": {
        "h": 8,
        "w": 6,
        "x": 0,
        "y": 8
      },
      "id": 4,
      "options": {
        "orientation": "auto",
        "reduceOptions": {
          "calcs": [
            "lastNotNull"
          ],
          "fields": "",
          "values": false
        },
        "showThresholdLabels": false,
        "showThresholdMarkers": true
      },
      "pluginVersion": "9.5.2",
      "targets": [
        {
          "datasource": {
            "type": "influxdb",
            "uid": "influxdb"
          },
          "query": "from(bucket: \"device_data\")\n  |> range(start: v.timeRangeStart, stop: v.timeRangeStop)\n  |> filter(fn: (r) => r[\"_measurement\"] == \"sensors\")\n  |> filter(fn: (r) => r[\"_field\"] == \"temperature\")\n  |> last()",
          "refId": "A"
        }
      ],
      "title": "当前温度",
      "type": "gauge"
    },
    {
      "datasource": {
        "type": "influxdb",
        "uid": "influxdb"
      },
      "fieldConfig": {
        "defaults": {
          "color": {
            "mode": "thresholds"
          },
          "mappings": [],
          "max": 100,
          "min": 0,
          "thresholds": {
            "mode": "absolute",
            "steps": [
              {
                "color": "red",
                "value": null
              },
              {
                "color": "yellow",
                "value": 30
              },
              {
                "color": "green",
                "value": 40
              },
              {
                "color": "yellow",
                "value": 70
              },
              {
                "color": "red",
                "value": 80
              }
            ]
          },
          "unit": "percent"
        },
        "overrides": []
      },
      "gridPos": {
        "h": 8,
        "w": 6,
        "x": 6,
        "y": 8
      },
      "id": 5,
      "options": {
        "orientation": "auto",
        "reduceOptions": {
          "calcs": [
            "lastNotNull"
          ],
          "fields": "",
          "values": false
        },
        "showThresholdLabels": false,
        "showThresholdMarkers": true
      },
      "pluginVersion": "9.5.2",
      "targets": [
        {
          "datasource": {
            "type": "influxdb",
            "uid": "influxdb"
          },
          "query": "from(bucket: \"device_data\")\n  |> range(start: v.timeRangeStart, stop: v.timeRangeStop)\n  |> filter(fn: (r) => r[\"_measurement\"] == \"sensors\")\n  |> filter(fn: (r) => r[\"_field\"] == \"humidity\")\n  |> last()",
          "refId": "A"
        }
      ],
      "title": "当前湿度",
      "type": "gauge"
    },
    {
      "datasource": {
        "type": "influxdb",
        "uid": "influxdb"
      },
      "fieldConfig": {
        "defaults": {
          "color": {
            "mode": "palette-classic"
          },
          "custom": {
            "hideFrom": {
              "legend": false,
              "tooltip": false,
              "viz": false
            }
          },
          "mappings": []
        },
        "overrides": []
      },
      "gridPos": {
        "h": 8,
        "w": 12,
        "x": 12,
        "y": 8
      },
      "id": 6,
      "options": {
        "displayLabels": [
          "name",
          "value",
          "percent"
        ],
        "legend": {
          "displayMode": "list",
          "placement": "bottom",
          "showLegend": true
        },
        "pieType": "pie",
        "reduceOptions": {
          "calcs": [
            "sum"
          ],
          "fields": "",
          "values": false
        },
        "tooltip": {
          "mode": "single",
          "sort": "none"
        }
      },
      "pluginVersion": "9.5.2",
      "targets": [
        {
          "datasource": {
            "type": "influxdb",
            "uid": "influxdb"
          },
          "query": "from(bucket: \"device_data\")\n  |> range(start: v.timeRangeStart, stop: v.timeRangeStop)\n  |> filter(fn: (r) => r[\"_measurement\"] == \"events\")\n  |> filter(fn: (r) => r[\"event_type\"] == \"alert\")\n  |> group(columns: [\"severity\"])\n  |> count()",
          "refId": "A"
        }
      ],
      "title": "告警分布",
      "type": "piechart"
    },
    {
      "datasource": {
        "type": "influxdb",
        "uid": "influxdb"
      },
      "fieldConfig": {
        "defaults": {
          "color": {
            "mode": "thresholds"
          },
          "custom": {
            "align": "auto",
            "cellOptions": {
              "type": "auto"
            },
            "inspect": false
          },
          "mappings": [],
          "thresholds": {
            "mode": "absolute",
            "steps": [
              {
                "color": "green",
                "value": null
              },
              {
                "color": "yellow",
                "value": 20
              },
              {
                "color": "red",
                "value": 40
              }
            ]
          }
        },
        "overrides": [
          {
            "matcher": {
              "id": "byName",
              "options": "severity"
            },
            "properties": [
              {
                "id": "custom.cellOptions",
                "value": {
                  "type": "color-text"
                }
              },
              {
                "id": "mappings",
                "value": [
                  {
                    "options": {
                      "danger": {
                        "color": "red",
                        "index": 2
                      },
                      "info": {
                        "color": "blue",
                        "index": 0
                      },
                      "warning": {
                        "color": "orange",
                        "index": 1
                      }
                    },
                    "type": "value"
                  }
                ]
              }
            ]
          },
          {
            "matcher": {
              "id": "byName",
              "options": "Time"
            },
            "properties": [
              {
                "id": "custom.width",
                "value": 170
              }
            ]
          }
        ]
      },
      "gridPos": {
        "h": 8,
        "w": 24,
        "x": 0,
        "y": 16
      },
      "id": 7,
      "options": {
        "footer": {
          "countRows": false,
          "fields": "",
          "reducer": [
            "sum"
          ],
          "show": false
        },
        "showHeader": true
      },
      "pluginVersion": "9.5.2",
      "targets": [
        {
          "datasource": {
            "type": "influxdb",
            "uid": "influxdb"
          },
          "query": "from(bucket: \"device_data\")\n  |> range(start: v.timeRangeStart, stop: v.timeRangeStop)\n  |> filter(fn: (r) => r[\"_measurement\"] == \"events\")\n  |> filter(fn: (r) => r[\"_field\"] == \"description\")\n  |> group(columns: [\"device_id\", \"severity\", \"event_type\"])\n  |> sort(columns: [\"_time\"], desc: true)\n  |> limit(n: 20)",
          "refId": "A"
        }
      ],
      "title": "最近事件",
      "type": "table"
    }
  ],
  "refresh": "5s",
  "schemaVersion": 38,
  "style": "dark",
  "tags": [],
  "templating": {
    "list": []
  },
  "time": {
    "from": "now-6h",
    "to": "now"
  },
  "timepicker": {},
  "timezone": "",
  "title": "AI智能监控平台",
  "uid": "ai-mqtt-monitoring",
  "version": 1,
  "weekStart": ""
} 